dp/__init__.py
dp/asr.py
dp/audio.py
dp/constants.py
dp/da.py
dp/darknet.py
dp/face.py
dp/hadoop.py
dp/resnet.py
dp/robot.py
dp/tts.py
dp/utils.py
dp/vgg.py
dp/data/da/parser/animal-dinosaur/pattern.dict
dp/data/da/parser/animal-dinosaur/synonym.dict
dp/data/da/parser/animal-dinosaur/term/category.dict
dp/data/da/parser/animal-dinosaur/term/field.dict
dp/data/da/parser/animal-dinosaur/term/ignore.dict
dp/data/da/parser/animal-dinosaur/term/order.dict
dp/data/da/parser/car-buy/pattern.dict
dp/data/da/parser/car-buy/synonym.dict
dp/data/da/parser/car-buy/term/brand.dict
dp/data/da/parser/car-buy/term/buy.dict
dp/data/da/parser/car-buy/term/field.dict
dp/data/da/parser/car-buy/term/ignore.dict
dp/data/da/parser/car-buy/term/order.dict
dp/data/da/parser/car-buy/term/series.dict
dp/data/da/parser/car-buy/term/year.dict
dp/data/da/trigger/animal-dinosaur.dict
dp/data/da/trigger/car-buy.dict
dp/data/facedb/faceid/SteveWong.健翔.jpg
dp/data/facedb/faceid/clj.崔丽娟.jpg
dp/data/facedb/faceid/cx.翔哥.jpg
dp/data/facedb/faceid/cx.陈翔.jpg
dp/data/facedb/faceid/cxp.崔骁鹏.jpg
dp/data/facedb/faceid/cxp.骁鹏.jpg
dp/data/facedb/faceid/czh.陈正浩.jpg
dp/data/facedb/faceid/ghl.翯龙.jpg
dp/data/facedb/faceid/gj.郭俊.jpg
dp/data/facedb/faceid/hcw.丛薇.jpg
dp/data/facedb/faceid/hjx.健翔.jpg
dp/data/facedb/faceid/jn.姜宁.jpg
dp/data/facedb/faceid/lam.芦爱梅.jpg
dp/data/facedb/faceid/lb.刘博.jpg
dp/data/facedb/faceid/lc.刘晨.jpg
dp/data/facedb/faceid/lhj.海军.jpg
dp/data/facedb/faceid/lp.普神.jpg
dp/data/facedb/faceid/lyj.梁阳建.jpg
dp/data/facedb/faceid/lzj.子嘉.jpg
dp/data/facedb/faceid/mcx.晨铉.jpg
dp/data/facedb/faceid/mjs.君生.jpg
dp/data/facedb/faceid/mly.丽媛.jpg
dp/data/facedb/faceid/mly.毛丽媛.jpg
dp/data/facedb/faceid/ssd.士达.jpg
dp/data/facedb/faceid/ssd.沈世达.jpg
dp/data/facedb/faceid/wc.丛哥.jpg
dp/data/facedb/faceid/wc.王丛.jpg
dp/data/facedb/faceid/wl.吴雷.jpg
dp/data/facedb/faceid/wyx.毅轩.jpg
dp/data/facedb/faceid/xh.肖含.jpg
dp/data/facedb/faceid/yan.抱小猪.jpg
pydp-0.1.16.dist-info/METADATA
pydp-0.1.16.dist-info/RECORD
pydp-0.1.16.dist-info/WHEEL
pydp-0.1.16.dist-info/top_level.txt
