Metadata-Version: 2.1
Name: pydp
Version: 0.1.16
Summary: Data Processing Lib
Home-page: http://www.yanjingang.com/docs/pydp/dp.html
Author-email: yanjingang@mail.com
License: UNKNOWN
Platform: UNKNOWN
Requires-Dist: numpy
Requires-Dist: opencv-python
Requires-Dist: pillow
Requires-Dist: pyquery
Requires-Dist: xpinyin
Requires-Dist: pyyaml
Requires-Dist: jieba
Requires-Dist: pydub
Requires-Dist: PyMySQL
Requires-Dist: pymongo
Requires-Dist: face-recognition
Requires-Dist: baidu-aip
Requires-Dist: tornado
Requires-Dist: python-chess (==0.27.0)
Requires-Dist: keras
